castberry/__init__.py
castberry/__main__.py
castberry/config.py
castberry/main.py
castberry/playlist.py
castberry/players/__init__.py
castberry/players/iplayer.py
castberry/players/vlc.py
castberry/resources/splash_screen.png
castberry/youtube/__init__.py
castberry/youtube/cast.py
castberry/youtube/video.py
castberry/youtube/resolvers/__init__.py
castberry/youtube/resolvers/cresolvers.py
castberry/youtube/resolvers/iresolver.py
castberry/youtube/resolvers/resgvi.py
castberry/youtube/resolvers/resytdl.py
castberry-0.1.dist-info/LICENSE
castberry-0.1.dist-info/METADATA
castberry-0.1.dist-info/WHEEL
castberry-0.1.dist-info/entry_points.txt
castberry-0.1.dist-info/top_level.txt
castberry-0.1.dist-info/RECORD
